UzbekStemmer/Suffixes.xml
UzbekStemmer/UzbekStemmer.py
UzbekStemmer/__init__.py
UzbekStemmer-0.2.6.dist-info/LICENSE
UzbekStemmer-0.2.6.dist-info/METADATA
UzbekStemmer-0.2.6.dist-info/WHEEL
UzbekStemmer-0.2.6.dist-info/top_level.txt
UzbekStemmer-0.2.6.dist-info/RECORD
