Metadata-Version: 2.1
Name: UzbekStemmer
Version: 0.2.6
Summary: Uzbek Stemmer for Python
Home-page: https://github.com/MaksudSharipov/UzbekStemmer
Author: Maksud Sharipov, Ulugbek Salaev, Ollabergan Yuldashev, Jasur Sobirov
Author-email: maqsbek72@gmail.com, ulugbek0302@gmail.com, ollaberganyuldashov@gmail.com
License: UNKNOWN
Project-URL: Bug Tracker, https://github.com/MaksudSharipov/UzbekStemmer
Platform: UNKNOWN
Classifier: Programming Language :: Python :: 3
Classifier: License :: OSI Approved :: MIT License
Classifier: Operating System :: OS Independent
Requires-Python: >=3.9
License-File: LICENSE
Requires-Dist: nltk
Requires-Dist: lxml
